odoo/addons/coupon_limit/README.rst
odoo/addons/coupon_limit/__init__.py
odoo/addons/coupon_limit/__manifest__.py
odoo/addons/coupon_limit/i18n/coupon_limit.pot
odoo/addons/coupon_limit/i18n/it.po
odoo/addons/coupon_limit/migrations/14.0.1.0.0/pre-migration.py
odoo/addons/coupon_limit/models/__init__.py
odoo/addons/coupon_limit/models/coupon_rule.py
odoo/addons/coupon_limit/readme/CONTRIBUTORS.rst
odoo/addons/coupon_limit/readme/DESCRIPTION.rst
odoo/addons/coupon_limit/security/ir.model.access.csv
odoo/addons/coupon_limit/static/description/icon.png
odoo/addons/coupon_limit/static/description/icon.svg
odoo/addons/coupon_limit/static/description/index.html
odoo/addons/coupon_limit/tests/__init__.py
odoo/addons/coupon_limit/tests/test_coupon_limit.py
odoo/addons/coupon_limit/views/coupon_program_views.xml
odoo14_addon_coupon_limit-14.0.1.0.1.dev6.dist-info/METADATA
odoo14_addon_coupon_limit-14.0.1.0.1.dev6.dist-info/WHEEL
odoo14_addon_coupon_limit-14.0.1.0.1.dev6.dist-info/top_level.txt
odoo14_addon_coupon_limit-14.0.1.0.1.dev6.dist-info/RECORD
